{
  "tender_id": "MABUMBE-2026-004",
  "institution": "mabumbe",
  "institution_name": "Bank of Africa Tanzania Limited",
  "title": "Supply, Implementation and Installation of Reconciliation Tool",
  "description": "Bank of Africa Tanzania Limited (BOAT) invites tenders for the supply, implementation, and installation of a reconciliation tool.",
  "reference_number": null,
  "published_date": "2026-02-25",
  "closing_date": "2026-03-25",
  "closing_time": null,
  "category": "ICT/Banking Systems",
  "status": "active",
  "source_url": "https://mabumbe.net/tenders/supply-and-installation-of-reconciliation-tool-tender-bank-of-africa-tanzania-march-2026/",
  "documents": [],
  "contact": {
    "name": "Bank of Africa Tanzania Limited",
    "email": null,
    "phone": null,
    "address": "Dar es Salaam, Tanzania"
  },
  "eligibility": "Details behind Mabumbe paywall",
  "bid_security": null,
  "scraped_at": "2026-03-13T06:00:00Z",
  "last_checked": "2026-03-13T06:00:00Z",
  "scrape_notes": "Detail page behind Mabumbe paywall. Title and dates from listing/search page."
}
